VideoChatBot/__init__.py
VideoChatBot-0.0.2.dist-info/LICENSE
VideoChatBot-0.0.2.dist-info/METADATA
VideoChatBot-0.0.2.dist-info/WHEEL
VideoChatBot-0.0.2.dist-info/top_level.txt
VideoChatBot-0.0.2.dist-info/RECORD
