Metadata-Version: 2.1
Name: VideoChatBot
Version: 0.0.2
Summary: VideoChat with a bot
Home-page: https://github.com/avaish1409/VideoChatBot
Author: Anirudh Vaish
Author-email: anirudhvaish147@gmail.com
License: UNKNOWN
Platform: UNKNOWN
Classifier: Programming Language :: Python :: 3.6
Classifier: Operating System :: OS Independent
Requires-Python: >=3.6
Requires-Dist: ChatterBot
Requires-Dist: opencv-python
Requires-Dist: SpeechRecognition
Requires-Dist: matplotlib
Requires-Dist: imageio
Requires-Dist: pyttsx3
Requires-Dist: text2emotion
Requires-Dist: tensorflow
Requires-Dist: fer
